filecensus/__init__.py
tests/__init__.py
tests/test_filecensus.py
FileCensus-4.42.10.dist-info/METADATA
FileCensus-4.42.10.dist-info/WHEEL
FileCensus-4.42.10.dist-info/top_level.txt
FileCensus-4.42.10.dist-info/RECORD
