Metadata-Version: 2.1
Name: FileCensus
Version: 4.42.10
Summary: FileCensus provides the insights and answers to what is claiming your storage space. and why.
Home-page: https://intermine.com
Author: Scott McCallum (https intermine.com)
Author-email: Sales@Intermine.com
License: UNKNOWN
Platform: UNKNOWN
Classifier: Programming Language :: Python :: 3
Classifier: Operating System :: OS Independent
Requires-Python: >=3.6
